osmrx/__init__.py
osmrx/apis_handler/__init__.py
osmrx/apis_handler/core.py
osmrx/apis_handler/models.py
osmrx/apis_handler/nominatim.py
osmrx/apis_handler/overpass.py
osmrx/apis_handler/query_builder.py
osmrx/data_processing/__init__.py
osmrx/data_processing/overpass_data_builder.py
osmrx/globals/queries.py
osmrx/helpers/__init__.py
osmrx/helpers/logger.py
osmrx/helpers/misc.py
osmrx/main/core.py
osmrx/main/pois.py
osmrx/main/roads.py
osmrx/network/__init__.py
osmrx/network/arc_feature.py
osmrx/network/isochrones_feature.py
osmrx/network/network_rx.py
osmrx/network/path_feature.py
osmrx/topology/__init__.py
osmrx/topology/checker.py
osmrx/topology/cleaner.py
osmrx-0.3.0.dist-info/LICENSE
osmrx-0.3.0.dist-info/WHEEL
osmrx-0.3.0.dist-info/METADATA
osmrx-0.3.0.dist-info/RECORD
