Metadata-Version: 2.1
Name: osmrx
Version: 0.3.0
Summary: 
Author: amauryval
Author-email: amauryval@gmail.com
Requires-Python: ==3.13.1
Classifier: Programming Language :: Python :: 3
Requires-Dist: matplotlib (>=3.10.0,<4.0.0)
Requires-Dist: more-itertools (>=10.5.0,<11.0.0)
Requires-Dist: pyproj (>=3.7.0,<4.0.0)
Requires-Dist: requests-futures (>=1.0.2,<2.0.0)
Requires-Dist: rtree (>=1.3.0,<2.0.0)
Requires-Dist: rustworkx[mpl] (==0.15.1)
Requires-Dist: scipy (>=1.14.1,<2.0.0)
Requires-Dist: setuptools (>=75.6.0,<76.0.0)
Requires-Dist: shapely (>=2.0.6,<3.0.0)
